[{"token": "Query", "bytes": [81, 117, 101, 114, 121], "logprob": -0.35510525, "top_logprobs": []}, {"token": ":", "bytes": [58], "logprob": -0.0015486642, "top_logprobs": []}, {"token": " \"", "bytes": [32, 34], "logprob": -4.2272506e-05, "top_logprobs": []}, {"token": "I", "bytes": [73], "logprob": -0.4063372, "top_logprobs": []}, {"token": "'m", "bytes": [39, 109], "logprob": -0.03538665, "top_logprobs": []}, {"token": " trying", "bytes": [32, 116, 114, 121, 105, 110, 103], "logprob": -4.1032944, "top_logprobs": []}, {"token": " to", "bytes": [32, 116, 111], "logprob": -4.4849444e-06, "top_logprobs": []}, {"token": " decide", "bytes": [32, 100, 101, 99, 105, 100, 101], "logprob": -0.03701627, "top_logprobs": []}, {"token": " what", "bytes": [32, 119, 104, 97, 116], "logprob": -0.13389812, "top_logprobs": []}, {"token": " to", "bytes": [32, 116, 111], "logprob": -0.07320462, "top_logprobs": []}, {"token": " watch", "bytes": [32, 119, 97, 116, 99, 104], "logprob": -0.00020914296, "top_logprobs": []}, {"token": ".", "bytes": [46], "logprob": -2.0672922, "top_logprobs": []}, {"token": " Do", "bytes": [32, 68, 111], "logprob": -2.3573022, "top_logprobs": []}, {"token": " you", "bytes": [32, 121, 111, 117], "logprob": -0.0073451274, "top_logprobs": []}, {"token": " know", "bytes": [32, 107, 110, 111, 119], "logprob": -0.8002758, "top_logprobs": []}, {"token": " if", "bytes": [32, 105, 102], "logprob": -0.011371533, "top_logprobs": []}, {"token": " the", "bytes": [32, 116, 104, 101], "logprob": -0.7865972, "top_logprobs": []}, {"token": " movie", "bytes": [32, 109, 111, 118, 105, 101], "logprob": -0.0073061916, "top_logprobs": []}, {"token": " Ant", "bytes": [32, 65, 110, 116], "logprob": -1.3259498, "top_logprobs": []}, {"token": "-Man", "bytes": [45, 77, 97, 110], "logprob": -5.145119e-05, "top_logprobs": []}, {"token": " is", "bytes": [32, 105, 115], "logprob": -0.00041315364, "top_logprobs": []}, {"token": " available", "bytes": [32, 97, 118, 97, 105, 108, 97, 98, 108, 101], "logprob": -0.00091824715, "top_logprobs": []}, {"token": " on", "bytes": [32, 111, 110], "logprob": -0.014842129, "top_logprobs": []}, {"token": " any", "bytes": [32, 97, 110, 121], "logprob": -3.1186566e-05, "top_logprobs": []}, {"token": " streaming", "bytes": [32, 115, 116, 114, 101, 97, 109, 105, 110, 103], "logprob": -0.00013536324, "top_logprobs": []}, {"token": " platforms", "bytes": [32, 112, 108, 97, 116, 102, 111, 114, 109, 115], "logprob": -0.0759277, "top_logprobs": []}, {"token": "?\"\n", "bytes": [63, 34, 10], "logprob": -0.0627312, "top_logprobs": []}, {"token": "Named", "bytes": [78, 97, 109, 101, 100], "logprob": -5.3193703e-06, "top_logprobs": []}, {"token": " Entities", "bytes": [32, 69, 110, 116, 105, 116, 105, 101, 115], "logprob": -3.9650025e-05, "top_logprobs": []}, {"token": ":", "bytes": [58], "logprob": -7.107425e-06, "top_logprobs": []}, {"token": " [", "bytes": [32, 91], "logprob": -0.00045057258, "top_logprobs": []}, {"token": "Ant", "bytes": [65, 110, 116], "logprob": -0.00023512568, "top_logprobs": []}, {"token": "-Man", "bytes": [45, 77, 97, 110], "logprob": -3.4524266e-05, "top_logprobs": []}, {"token": " (", "bytes": [32, 40], "logprob": -7.703444e-06, "top_logprobs": []}, {"token": "Title", "bytes": [84, 105, 116, 108, 101], "logprob": -5.4385737e-06, "top_logprobs": []}, {"token": ")]\n\n", "bytes": [41, 93, 10, 10], "logprob": -1.9956058, "top_logprobs": []}, {"token": "Query", "bytes": [81, 117, 101, 114, 121], "logprob": -1.504853e-06, "top_logprobs": []}, {"token": ":", "bytes": [58], "logprob": -4.8425554e-06, "top_logprobs": []}, {"token": " \"", "bytes": [32, 34], "logprob": -2.9352968e-06, "top_logprobs": []}, {"token": "I", "bytes": [73], "logprob": -0.067998745, "top_logprobs": []}, {"token": "'m", "bytes": [39, 109], "logprob": -0.2130222, "top_logprobs": []}, {"token": " in", "bytes": [32, 105, 110], "logprob": -0.3193375, "top_logprobs": []}, {"token": " the", "bytes": [32, 116, 104, 101], "logprob": -0.00010640408, "top_logprobs": []}, {"token": " mood", "bytes": [32, 109, 111, 111, 100], "logprob": 0.0, "top_logprobs": []}, {"token": " for", "bytes": [32, 102, 111, 114], "logprob": -0.00076686393, "top_logprobs": []}, {"token": " a", "bytes": [32, 97], "logprob": -0.33858168, "top_logprobs": []}, {"token": " survival", "bytes": [32, 115, 117, 114, 118, 105, 118, 97, 108], "logprob": -0.5943583, "top_logprobs": []}, {"token": " adventure", "bytes": [32, 97, 100, 118, 101, 110, 116, 117, 114, 101], "logprob": -1.2948405e-05, "top_logprobs": []}, {"token": ".", "bytes": [46], "logprob": -2.9765441, "top_logprobs": []}, {"token": " Any", "bytes": [32, 65, 110, 121], "logprob": -1.614725, "top_logprobs": []}, {"token": " idea", "bytes": [32, 105, 100, 101, 97], "logprob": -0.86867034, "top_logprobs": []}, {"token": " where", "bytes": [32, 119, 104, 101, 114, 101], "logprob": -0.24618483, "top_logprobs": []}, {"token": " I", "bytes": [32, 73], "logprob": -0.00018995117, "top_logprobs": []}, {"token": " can", "bytes": [32, 99, 97, 110], "logprob": -0.030925944, "top_logprobs": []}, {"token": " find", "bytes": [32, 102, 105, 110, 100], "logprob": -0.14305978, "top_logprobs": []}, {"token": " a", "bytes": [32, 97], "logprob": -0.024644265, "top_logprobs": []}, {"token": " movie", "bytes": [32, 109, 111, 118, 105, 101], "logprob": -0.6536077, "top_logprobs": []}, {"token": " with", "bytes": [32, 119, 105, 116, 104], "logprob": -1.261358, "top_logprobs": []}, {"token": " that", "bytes": [32, 116, 104, 97, 116], "logprob": -0.23429622, "top_logprobs": []}, {"token": " theme", "bytes": [32, 116, 104, 101, 109, 101], "logprob": -0.47032127, "top_logprobs": []}, {"token": "?\"\n", "bytes": [63, 34, 10], "logprob": -1.3862745, "top_logprobs": []}, {"token": "Named", "bytes": [78, 97, 109, 101, 100], "logprob": -6.9882217e-06, "top_logprobs": []}, {"token": " Entities", "bytes": [32, 69, 110, 116, 105, 116, 105, 101, 115], "logprob": -1.7716551e-05, "top_logprobs": []}, {"token": ":", "bytes": [58], "logprob": -1.1756368e-05, "top_logprobs": []}, {"token": " [", "bytes": [32, 91], "logprob": -9.0883464e-07, "top_logprobs": []}, {"token": "sur", "bytes": [115, 117, 114], "logprob": -0.017780425, "top_logprobs": []}, {"token": "v", "bytes": [118], "logprob": -4.3202e-07, "top_logprobs": []}, {"token": "ival", "bytes": [105, 118, 97, 108], "logprob": -2.1008714e-06, "top_logprobs": []}, {"token": " adventure", "bytes": [32, 97, 100, 118, 101, 110, 116, 117, 114, 101], "logprob": -4.365741e-06, "top_logprobs": []}, {"token": " (", "bytes": [32, 40], "logprob": -1.2233183e-05, "top_logprobs": []}, {"token": "Genre", "bytes": [71, 101, 110, 114, 101], "logprob": -4.5848617e-05, "top_logprobs": []}, {"token": ")]\n\n", "bytes": [41, 93, 10, 10], "logprob": -0.00073434337, "top_logprobs": []}, {"token": "Query", "bytes": [81, 117, 101, 114, 121], "logprob": -1.8624639e-06, "top_logprobs": []}, {"token": ":", "bytes": [58], "logprob": -5.080963e-06, "top_logprobs": []}, {"token": " \"", "bytes": [32, 34], "logprob": -1.7432603e-06, "top_logprobs": []}, {"token": "I", "bytes": [73], "logprob": -0.0012542768, "top_logprobs": []}, {"token": "'m", "bytes": [39, 109], "logprob": -0.38704714, "top_logprobs": []}, {"token": " not", "bytes": [32, 110, 111, 116], "logprob": -2.8150268, "top_logprobs": []}, {"token": " sure", "bytes": [32, 115, 117, 114, 101], "logprob": -0.00017171667, "top_logprobs": []}, {"token": " what", "bytes": [32, 119, 104, 97, 116], "logprob": -0.0002451278, "top_logprobs": []}, {"token": " to", "bytes": [32, 116, 111], "logprob": -0.0061100936, "top_logprobs": []}, {"token": " watch", "bytes": [32, 119, 97, 116, 99, 104], "logprob": -0.0063131624, "top_logprobs": []}, {"token": ".", "bytes": [46], "logprob": -0.6417297, "top_logprobs": []}, {"token": " Can", "bytes": [32, 67, 97, 110], "logprob": -0.16009808, "top_logprobs": []}, {"token": " you", "bytes": [32, 121, 111, 117], "logprob": -0.4647155, "top_logprobs": []}, {"token": " help", "bytes": [32, 104, 101, 108, 112], "logprob": -0.15529202, "top_logprobs": []}, {"token": " me", "bytes": [32, 109, 101], "logprob": -0.0001501445, "top_logprobs": []}, {"token": " find", "bytes": [32, 102, 105, 110, 100], "logprob": -0.0008741821, "top_logprobs": []}, {"token": " a", "bytes": [32, 97], "logprob": -0.0006971848, "top_logprobs": []}, {"token": " movie", "bytes": [32, 109, 111, 118, 105, 101], "logprob": -1.110729, "top_logprobs": []}, {"token": " with", "bytes": [32, 119, 105, 116, 104], "logprob": -0.50339025, "top_logprobs": []}, {"token": " a", "bytes": [32, 97], "logprob": -0.10988168, "top_logprobs": []}, {"token": " plot", "bytes": [32, 112, 108, 111, 116], "logprob": -5.991829, "top_logprobs": []}, {"token": " related", "bytes": [32, 114, 101, 108, 97, 116, 101, 100], "logprob": -0.17436503, "top_logprobs": []}, {"token": " to", "bytes": [32, 116, 111], "logprob": -3.1281633e-07, "top_logprobs": []}, {"token": " cyber", "bytes": [32, 99, 121, 98, 101, 114], "logprob": -0.0020086954, "top_logprobs": []}, {"token": "crime", "bytes": [99, 114, 105, 109, 101], "logprob": -1.0445127e-05, "top_logprobs": []}, {"token": "?\"\n", "bytes": [63, 34, 10], "logprob": -0.5457537, "top_logprobs": []}, {"token": "Named", "bytes": [78, 97, 109, 101, 100], "logprob": -3.5313153e-06, "top_logprobs": []}, {"token": " Entities", "bytes": [32, 69, 110, 116, 105, 116, 105, 101, 115], "logprob": -1.6524515e-05, "top_logprobs": []}, {"token": ":", "bytes": [58], "logprob": -1.378283e-05, "top_logprobs": []}, {"token": " [", "bytes": [32, 91], "logprob": -2.577686e-06, "top_logprobs": []}, {"token": "cy", "bytes": [99, 121], "logprob": -0.0072369566, "top_logprobs": []}, {"token": "ber", "bytes": [98, 101, 114], "logprob": -3.1737043e-06, "top_logprobs": []}, {"token": "crime", "bytes": [99, 114, 105, 109, 101], "logprob": -1.8624639e-06, "top_logprobs": []}, {"token": " (", "bytes": [32, 40], "logprob": -1.3856493e-06, "top_logprobs": []}, {"token": "Plot", "bytes": [80, 108, 111, 116], "logprob": -0.00081355876, "top_logprobs": []}, {"token": ")]", "bytes": [41, 93], "logprob": -0.0007657911, "top_logprobs": []}]