[{"token": "1", "bytes": [49], "logprob": -0.18195741, "top_logprobs": []}, {"token": ".", "bytes": [46], "logprob": -8.418666e-06, "top_logprobs": []}, {"token": " \"", "bytes": [32, 34], "logprob": -0.15256073, "top_logprobs": []}, {"token": "Please", "bytes": [80, 108, 101, 97, 115, 101], "logprob": -5.934335, "top_logprobs": []}, {"token": " recommend", "bytes": [32, 114, 101, 99, 111, 109, 109, 101, 110, 100], "logprob": -0.081525475, "top_logprobs": []}, {"token": " a", "bytes": [32, 97], "logprob": -0.045867458, "top_logprobs": []}, {"token": " restaurant", "bytes": [32, 114, 101, 115, 116, 97, 117, 114, 97, 110, 116], "logprob": -0.5999325, "top_logprobs": []}, {"token": " with", "bytes": [32, 119, 105, 116, 104], "logprob": -0.21961106, "top_logprobs": []}, {"token": " outdoor", "bytes": [32, 111, 117, 116, 100, 111, 111, 114], "logprob": -0.6322806, "top_logprobs": []}, {"token": " seating", "bytes": [32, 115, 101, 97, 116, 105, 110, 103], "logprob": -0.0026275003, "top_logprobs": []}, {"token": " near", "bytes": [32, 110, 101, 97, 114], "logprob": -0.2806107, "top_logprobs": []}, {"token": " Land", "bytes": [32, 76, 97, 110, 100], "logprob": -0.6679974, "top_logprobs": []}, {"token": "marks", "bytes": [109, 97, 114, 107, 115], "logprob": -0.00092587253, "top_logprobs": []}, {"token": " in", "bytes": [32, 105, 110], "logprob": -0.22883914, "top_logprobs": []}, {"token": " Toronto", "bytes": [32, 84, 111, 114, 111, 110, 116, 111], "logprob": -0.001298331, "top_logprobs": []}, {"token": ".\"\n", "bytes": [46, 34, 10], "logprob": -0.9586116, "top_logprobs": []}, {"token": "Named", "bytes": [78, 97, 109, 101, 100], "logprob": -0.080113985, "top_logprobs": []}, {"token": " Entities", "bytes": [32, 69, 110, 116, 105, 116, 105, 101, 115], "logprob": -0.00010974178, "top_logprobs": []}, {"token": ":", "bytes": [58], "logprob": -2.3392786e-06, "top_logprobs": []}, {"token": " [", "bytes": [32, 91], "logprob": -2.577686e-06, "top_logprobs": []}, {"token": "restaurant", "bytes": [114, 101, 115, 116, 97, 117, 114, 97, 110, 116], "logprob": -4.555724, "top_logprobs": []}, {"token": " (", "bytes": [32, 40], "logprob": -0.0030052734, "top_logprobs": []}, {"token": "A", "bytes": [65], "logprob": -0.0017407472, "top_logprobs": []}, {"token": "men", "bytes": [109, 101, 110], "logprob": 0.0, "top_logprobs": []}, {"token": "ity", "bytes": [105, 116, 121], "logprob": -4.477578e-05, "top_logprobs": []}, {"token": "),", "bytes": [41, 44], "logprob": -2.1769476e-05, "top_logprobs": []}, {"token": " outdoor", "bytes": [32, 111, 117, 116, 100, 111, 111, 114], "logprob": -0.00014478032, "top_logprobs": []}, {"token": " seating", "bytes": [32, 115, 101, 97, 116, 105, 110, 103], "logprob": -0.00012868783, "top_logprobs": []}, {"token": " (", "bytes": [32, 40], "logprob": -5.6934558e-05, "top_logprobs": []}, {"token": "A", "bytes": [65], "logprob": -1.7835755e-05, "top_logprobs": []}, {"token": "men", "bytes": [109, 101, 110], "logprob": 0.0, "top_logprobs": []}, {"token": "ity", "bytes": [105, 116, 121], "logprob": -3.4285862e-05, "top_logprobs": []}, {"token": "),", "bytes": [41, 44], "logprob": -9.014684e-06, "top_logprobs": []}, {"token": " Land", "bytes": [32, 76, 97, 110, 100], "logprob": -0.0042201476, "top_logprobs": []}, {"token": "marks", "bytes": [109, 97, 114, 107, 115], "logprob": -8.697388e-05, "top_logprobs": []}, {"token": " (", "bytes": [32, 40], "logprob": -0.007848648, "top_logprobs": []}, {"token": "Location", "bytes": [76, 111, 99, 97, 116, 105, 111, 110], "logprob": -3.5313153e-06, "top_logprobs": []}, {"token": "),", "bytes": [41, 44], "logprob": -4.7517467e-05, "top_logprobs": []}, {"token": " Toronto", "bytes": [32, 84, 111, 114, 111, 110, 116, 111], "logprob": -1.378283e-05, "top_logprobs": []}, {"token": " (", "bytes": [32, 40], "logprob": -0.00048620347, "top_logprobs": []}, {"token": "Location", "bytes": [76, 111, 99, 97, 116, 105, 111, 110], "logprob": -3.4121115e-06, "top_logprobs": []}, {"token": ")]\n\n", "bytes": [41, 93, 10, 10], "logprob": -0.0013350017, "top_logprobs": []}, {"token": "2", "bytes": [50], "logprob": -1.3186812e-05, "top_logprobs": []}, {"token": ".", "bytes": [46], "logprob": -4.00813e-06, "top_logprobs": []}, {"token": " \"", "bytes": [32, 34], "logprob": -2.577686e-06, "top_logprobs": []}, {"token": "What", "bytes": [87, 104, 97, 116], "logprob": -1.3307687, "top_logprobs": []}, {"token": " are", "bytes": [32, 97, 114, 101], "logprob": -0.3154572, "top_logprobs": []}, {"token": " some", "bytes": [32, 115, 111, 109, 101], "logprob": -2.8741255, "top_logprobs": []}, {"token": " affordable", "bytes": [32, 97, 102, 102, 111, 114, 100, 97, 98, 108, 101], "logprob": -1.0961107, "top_logprobs": []}, {"token": " Italian", "bytes": [32, 73, 116, 97, 108, 105, 97, 110], "logprob": -0.47229847, "top_logprobs": []}, {"token": " restaurants", "bytes": [32, 114, 101, 115, 116, 97, 117, 114, 97, 110, 116, 115], "logprob": -0.045510586, "top_logprobs": []}, {"token": " in", "bytes": [32, 105, 110], "logprob": -2.4809785, "top_logprobs": []}, {"token": " the", "bytes": [32, 116, 104, 101], "logprob": -0.34692153, "top_logprobs": []}, {"token": " downtown", "bytes": [32, 100, 111, 119, 110, 116, 111, 119, 110], "logprob": -0.13873589, "top_logprobs": []}, {"token": " area", "bytes": [32, 97, 114, 101, 97], "logprob": -0.039469127, "top_logprobs": []}, {"token": " of", "bytes": [32, 111, 102], "logprob": -0.03473436, "top_logprobs": []}, {"token": " Toronto", "bytes": [32, 84, 111, 114, 111, 110, 116, 111], "logprob": -4.604148e-06, "top_logprobs": []}, {"token": "?\"\n", "bytes": [63, 34, 10], "logprob": -0.003727869, "top_logprobs": []}, {"token": "Named", "bytes": [78, 97, 109, 101, 100], "logprob": -4.1273333e-06, "top_logprobs": []}, {"token": " Entities", "bytes": [32, 69, 110, 116, 105, 116, 105, 101, 115], "logprob": -2.5107178e-05, "top_logprobs": []}, {"token": ":", "bytes": [58], "logprob": -1.0683535e-05, "top_logprobs": []}, {"token": " [", "bytes": [32, 91], "logprob": -1.0280384e-06, "top_logprobs": []}, {"token": "aff", "bytes": [97, 102, 102], "logprob": -0.015894758, "top_logprobs": []}, {"token": "ordable", "bytes": [111, 114, 100, 97, 98, 108, 101], "logprob": -2.8206474e-05, "top_logprobs": []}, {"token": " (", "bytes": [32, 40], "logprob": -4.4849444e-06, "top_logprobs": []}, {"token": "Price", "bytes": [80, 114, 105, 99, 101], "logprob": -3.888926e-06, "top_logprobs": []}, {"token": "),", "bytes": [41, 44], "logprob": -7.89631e-07, "top_logprobs": []}, {"token": " Italian", "bytes": [32, 73, 116, 97, 108, 105, 97, 110], "logprob": -4.7755875e-05, "top_logprobs": []}, {"token": " (", "bytes": [32, 40], "logprob": -0.000119874094, "top_logprobs": []}, {"token": "C", "bytes": [67], "logprob": -4.9617593e-06, "top_logprobs": []}, {"token": "uisine", "bytes": [117, 105, 115, 105, 110, 101], "logprob": -1.504853e-06, "top_logprobs": []}, {"token": "),", "bytes": [41, 44], "logprob": -2.1008714e-06, "top_logprobs": []}, {"token": " downtown", "bytes": [32, 100, 111, 119, 110, 116, 111, 119, 110], "logprob": -3.1737043e-06, "top_logprobs": []}, {"token": " area", "bytes": [32, 97, 114, 101, 97], "logprob": -0.08891122, "top_logprobs": []}, {"token": " (", "bytes": [32, 40], "logprob": -0.21419895, "top_logprobs": []}, {"token": "Location", "bytes": [76, 111, 99, 97, 116, 105, 111, 110], "logprob": -4.3202e-07, "top_logprobs": []}, {"token": "),", "bytes": [41, 44], "logprob": -5.3193703e-06, "top_logprobs": []}, {"token": " Toronto", "bytes": [32, 84, 111, 114, 111, 110, 116, 111], "logprob": -3.5313153e-06, "top_logprobs": []}, {"token": " (", "bytes": [32, 40], "logprob": -3.1186566e-05, "top_logprobs": []}, {"token": "Location", "bytes": [76, 111, 99, 97, 116, 105, 111, 110], "logprob": -3.4121115e-06, "top_logprobs": []}, {"token": ")]\n\n", "bytes": [41, 93, 10, 10], "logprob": -0.0001693326, "top_logprobs": []}, {"token": "3", "bytes": [51], "logprob": -1.504853e-06, "top_logprobs": []}, {"token": ".", "bytes": [46], "logprob": -7.58424e-06, "top_logprobs": []}, {"token": " \"", "bytes": [32, 34], "logprob": -2.3392786e-06, "top_logprobs": []}, {"token": "I", "bytes": [73], "logprob": -0.66366535, "top_logprobs": []}, {"token": "'m", "bytes": [39, 109], "logprob": -0.34362027, "top_logprobs": []}, {"token": " craving", "bytes": [32, 99, 114, 97, 118, 105, 110, 103], "logprob": -0.190866, "top_logprobs": []}, {"token": " a", "bytes": [32, 97], "logprob": -3.951404, "top_logprobs": []}, {"token": " juicy", "bytes": [32, 106, 117, 105, 99, 121], "logprob": -0.96453995, "top_logprobs": []}, {"token": " burger", "bytes": [32, 98, 117, 114, 103, 101, 114], "logprob": -0.34358543, "top_logprobs": []}, {"token": ",", "bytes": [44], "logprob": -0.24733706, "top_logprobs": []}, {"token": " where", "bytes": [32, 119, 104, 101, 114, 101], "logprob": -0.45299333, "top_logprobs": []}, {"token": " can", "bytes": [32, 99, 97, 110], "logprob": -0.021760287, "top_logprobs": []}, {"token": " I", "bytes": [32, 73], "logprob": -1.0683535e-05, "top_logprobs": []}, {"token": " find", "bytes": [32, 102, 105, 110, 100], "logprob": -0.00092694536, "top_logprobs": []}, {"token": " a", "bytes": [32, 97], "logprob": -0.79436654, "top_logprobs": []}, {"token": " highly", "bytes": [32, 104, 105, 103, 104, 108, 121], "logprob": -0.5114459, "top_logprobs": []}, {"token": "-rated", "bytes": [45, 114, 97, 116, 101, 100], "logprob": -0.31994027, "top_logprobs": []}, {"token": " burger", "bytes": [32, 98, 117, 114, 103, 101, 114], "logprob": -0.0020370109, "top_logprobs": []}, {"token": " joint", "bytes": [32, 106, 111, 105, 110, 116], "logprob": -0.0017833562, "top_logprobs": []}, {"token": " in", "bytes": [32, 105, 110], "logprob": -0.63718677, "top_logprobs": []}, {"token": " Toronto", "bytes": [32, 84, 111, 114, 111, 110, 116, 111], "logprob": -0.17172882, "top_logprobs": []}, {"token": "?\"\n", "bytes": [63, 34, 10], "logprob": -0.0076260306, "top_logprobs": []}, {"token": "Named", "bytes": [78, 97, 109, 101, 100], "logprob": -3.1737043e-06, "top_logprobs": []}, {"token": " Entities", "bytes": [32, 69, 110, 116, 105, 116, 105, 101, 115], "logprob": -2.4630364e-05, "top_logprobs": []}, {"token": ":", "bytes": [58], "logprob": -9.729906e-06, "top_logprobs": []}, {"token": " [", "bytes": [32, 91], "logprob": -4.3202e-07, "top_logprobs": []}, {"token": "ju", "bytes": [106, 117], "logprob": -0.0041167503, "top_logprobs": []}, {"token": "icy", "bytes": [105, 99, 121], "logprob": -1.7432603e-06, "top_logprobs": []}, {"token": " burger", "bytes": [32, 98, 117, 114, 103, 101, 114], "logprob": -0.009028972, "top_logprobs": []}, {"token": " (", "bytes": [32, 40], "logprob": -3.1424974e-05, "top_logprobs": []}, {"token": "D", "bytes": [68], "logprob": -4.3202e-07, "top_logprobs": []}, {"token": "ish", "bytes": [105, 115, 104], "logprob": 0.0, "top_logprobs": []}, {"token": "),", "bytes": [41, 44], "logprob": -6.704273e-07, "top_logprobs": []}, {"token": " highly", "bytes": [32, 104, 105, 103, 104, 108, 121], "logprob": -2.6968896e-06, "top_logprobs": []}, {"token": "-rated", "bytes": [45, 114, 97, 116, 101, 100], "logprob": -1.2948405e-05, "top_logprobs": []}, {"token": " (", "bytes": [32, 40], "logprob": -6.704273e-07, "top_logprobs": []}, {"token": "Rating", "bytes": [82, 97, 116, 105, 110, 103], "logprob": -1.7432603e-06, "top_logprobs": []}, {"token": "),", "bytes": [41, 44], "logprob": -2.9352968e-06, "top_logprobs": []}, {"token": " burger", "bytes": [32, 98, 117, 114, 103, 101, 114], "logprob": -0.0060661365, "top_logprobs": []}, {"token": " joint", "bytes": [32, 106, 111, 105, 110, 116], "logprob": -6.6306106e-06, "top_logprobs": []}, {"token": " (", "bytes": [32, 40], "logprob": -3.4121115e-06, "top_logprobs": []}, {"token": "Restaurant", "bytes": [82, 101, 115, 116, 97, 117, 114, 97, 110, 116], "logprob": -0.084328786, "top_logprobs": []}, {"token": " Name", "bytes": [32, 78, 97, 109, 101], "logprob": -3.523949e-05, "top_logprobs": []}, {"token": "),", "bytes": [41, 44], "logprob": -3.2929079e-06, "top_logprobs": []}, {"token": " Toronto", "bytes": [32, 84, 111, 114, 111, 110, 116, 111], "logprob": -2.3676734e-05, "top_logprobs": []}, {"token": " (", "bytes": [32, 40], "logprob": -1.8074163e-05, "top_logprobs": []}, {"token": "Location", "bytes": [76, 111, 99, 97, 116, 105, 111, 110], "logprob": -2.8160932e-06, "top_logprobs": []}, {"token": ")]", "bytes": [41, 93], "logprob": -9.817902e-05, "top_logprobs": []}]