[{"token": "1", "bytes": [49], "logprob": -0.692257, "top_logprobs": []}, {"token": ".", "bytes": [46], "logprob": -2.1008714e-06, "top_logprobs": []}, {"token": " \"", "bytes": [32, 34], "logprob": -0.058574434, "top_logprobs": []}, {"token": "What", "bytes": [87, 104, 97, 116], "logprob": -2.835104, "top_logprobs": []}, {"token": " are", "bytes": [32, 97, 114, 101], "logprob": -1.4660413, "top_logprobs": []}, {"token": " the", "bytes": [32, 116, 104, 101], "logprob": -0.017244166, "top_logprobs": []}, {"token": " hours", "bytes": [32, 104, 111, 117, 114, 115], "logprob": -0.33804658, "top_logprobs": []}, {"token": " of", "bytes": [32, 111, 102], "logprob": -0.2987989, "top_logprobs": []}, {"token": " A", "bytes": [32, 65], "logprob": -0.33517125, "top_logprobs": []}, {"token": "roma", "bytes": [114, 111, 109, 97], "logprob": -7.89631e-07, "top_logprobs": []}, {"token": " Cafe", "bytes": [32, 67, 97, 102, 101], "logprob": -0.000105331244, "top_logprobs": []}, {"token": "?\"\n", "bytes": [63, 34, 10], "logprob": -0.6311185, "top_logprobs": []}, {"token": "Named", "bytes": [78, 97, 109, 101, 100], "logprob": -0.20035318, "top_logprobs": []}, {"token": " Entities", "bytes": [32, 69, 110, 116, 105, 116, 105, 101, 115], "logprob": -1.27099975e-05, "top_logprobs": []}, {"token": ":", "bytes": [58], "logprob": -1.7432603e-06, "top_logprobs": []}, {"token": " [", "bytes": [32, 91], "logprob": -2.1173457e-05, "top_logprobs": []}, {"token": "A", "bytes": [65], "logprob": -9.849109e-06, "top_logprobs": []}, {"token": "roma", "bytes": [114, 111, 109, 97], "logprob": -5.5122365e-07, "top_logprobs": []}, {"token": " Cafe", "bytes": [32, 67, 97, 102, 101], "logprob": -5.4550484e-05, "top_logprobs": []}, {"token": " (", "bytes": [32, 40], "logprob": -0.00015264409, "top_logprobs": []}, {"token": "Restaurant", "bytes": [82, 101, 115, 116, 97, 117, 114, 97, 110, 116], "logprob": -1.2829201e-05, "top_logprobs": []}, {"token": " Name", "bytes": [32, 78, 97, 109, 101], "logprob": -1.27099975e-05, "top_logprobs": []}, {"token": "),", "bytes": [41, 44], "logprob": -0.0011249757, "top_logprobs": []}, {"token": " hours", "bytes": [32, 104, 111, 117, 114, 115], "logprob": -0.01451545, "top_logprobs": []}, {"token": " (", "bytes": [32, 40], "logprob": -4.1080468e-05, "top_logprobs": []}, {"token": "Hours", "bytes": [72, 111, 117, 114, 115], "logprob": -0.0007761582, "top_logprobs": []}, {"token": ")]\n\n", "bytes": [41, 93, 10, 10], "logprob": -0.0006252298, "top_logprobs": []}, {"token": "2", "bytes": [50], "logprob": -1.3544423e-05, "top_logprobs": []}, {"token": ".", "bytes": [46], "logprob": -4.00813e-06, "top_logprobs": []}, {"token": " \"", "bytes": [32, 34], "logprob": -2.4584822e-06, "top_logprobs": []}, {"token": "Can", "bytes": [67, 97, 110], "logprob": -0.42651206, "top_logprobs": []}, {"token": " you", "bytes": [32, 121, 111, 117], "logprob": -0.00022690064, "top_logprobs": []}, {"token": " recommend", "bytes": [32, 114, 101, 99, 111, 109, 109, 101, 110, 100], "logprob": -0.012220119, "top_logprobs": []}, {"token": " the", "bytes": [32, 116, 104, 101], "logprob": -0.006215543, "top_logprobs": []}, {"token": " highest", "bytes": [32, 104, 105, 103, 104, 101, 115, 116], "logprob": -0.0014291671, "top_logprobs": []}, {"token": "-rated", "bytes": [45, 114, 97, 116, 101, 100], "logprob": -3.1737043e-06, "top_logprobs": []}, {"token": " seafood", "bytes": [32, 115, 101, 97, 102, 111, 111, 100], "logprob": -1.899093, "top_logprobs": []}, {"token": " restaurant", "bytes": [32, 114, 101, 115, 116, 97, 117, 114, 97, 110, 116], "logprob": -0.0020343957, "top_logprobs": []}, {"token": " in", "bytes": [32, 105, 110], "logprob": -0.06760162, "top_logprobs": []}, {"token": " the", "bytes": [32, 116, 104, 101], "logprob": -0.08580721, "top_logprobs": []}, {"token": " area", "bytes": [32, 97, 114, 101, 97], "logprob": -0.00052193523, "top_logprobs": []}, {"token": "?\"\n", "bytes": [63, 34, 10], "logprob": -0.00062582217, "top_logprobs": []}, {"token": "Named", "bytes": [78, 97, 109, 101, 100], "logprob": -3.1737043e-06, "top_logprobs": []}, {"token": " Entities", "bytes": [32, 69, 110, 116, 105, 116, 105, 101, 115], "logprob": -1.1637165e-05, "top_logprobs": []}, {"token": ":", "bytes": [58], "logprob": -1.2233183e-05, "top_logprobs": []}, {"token": " [", "bytes": [32, 91], "logprob": -5.5122365e-07, "top_logprobs": []}, {"token": "Highest", "bytes": [72, 105, 103, 104, 101, 115, 116], "logprob": -0.06584648, "top_logprobs": []}, {"token": "-rated", "bytes": [45, 114, 97, 116, 101, 100], "logprob": -3.888926e-06, "top_logprobs": []}, {"token": " (", "bytes": [32, 40], "logprob": -1.18755715e-05, "top_logprobs": []}, {"token": "Rating", "bytes": [82, 97, 116, 105, 110, 103], "logprob": -2.4584822e-06, "top_logprobs": []}, {"token": "),", "bytes": [41, 44], "logprob": -3.0545007e-06, "top_logprobs": []}, {"token": " seafood", "bytes": [32, 115, 101, 97, 102, 111, 111, 100], "logprob": -1.3902034e-05, "top_logprobs": []}, {"token": " (", "bytes": [32, 40], "logprob": -0.0038389063, "top_logprobs": []}, {"token": "C", "bytes": [67], "logprob": -1.6240566e-06, "top_logprobs": []}, {"token": "uisine", "bytes": [117, 105, 115, 105, 110, 101], "logprob": -9.0883464e-07, "top_logprobs": []}, {"token": ")]\n\n", "bytes": [41, 93, 10, 10], "logprob": -0.795043, "top_logprobs": []}, {"token": "3", "bytes": [51], "logprob": -1.504853e-06, "top_logprobs": []}, {"token": ".", "bytes": [46], "logprob": -7.822647e-06, "top_logprobs": []}, {"token": " \"", "bytes": [32, 34], "logprob": -1.9816675e-06, "top_logprobs": []}, {"token": "I", "bytes": [73], "logprob": -0.53152114, "top_logprobs": []}, {"token": "'m", "bytes": [39, 109], "logprob": -0.015628628, "top_logprobs": []}, {"token": " looking", "bytes": [32, 108, 111, 111, 107, 105, 110, 103], "logprob": -0.056843605, "top_logprobs": []}, {"token": " for", "bytes": [32, 102, 111, 114], "logprob": -1.0564331e-05, "top_logprobs": []}, {"token": " a", "bytes": [32, 97], "logprob": -0.00031520487, "top_logprobs": []}, {"token": " place", "bytes": [32, 112, 108, 97, 99, 101], "logprob": -0.7986589, "top_logprobs": []}, {"token": " with", "bytes": [32, 119, 105, 116, 104], "logprob": -0.026958233, "top_logprobs": []}, {"token": " outdoor", "bytes": [32, 111, 117, 116, 100, 111, 111, 114], "logprob": -0.2446154, "top_logprobs": []}, {"token": " seating", "bytes": [32, 115, 101, 97, 116, 105, 110, 103], "logprob": -0.00015753144, "top_logprobs": []}, {"token": " and", "bytes": [32, 97, 110, 100], "logprob": -0.11731089, "top_logprobs": []}, {"token": " a", "bytes": [32, 97], "logprob": -0.0063446616, "top_logprobs": []}, {"token": " diverse", "bytes": [32, 100, 105, 118, 101, 114, 115, 101], "logprob": -0.29199326, "top_logprobs": []}, {"token": " menu", "bytes": [32, 109, 101, 110, 117], "logprob": -0.0005965201, "top_logprobs": []}, {"token": ".\"\n", "bytes": [46, 34, 10], "logprob": -1.2957213, "top_logprobs": []}, {"token": "Named", "bytes": [78, 97, 109, 101, 100], "logprob": -3.4121115e-06, "top_logprobs": []}, {"token": " Entities", "bytes": [32, 69, 110, 116, 105, 116, 105, 101, 115], "logprob": -2.188868e-05, "top_logprobs": []}, {"token": ":", "bytes": [58], "logprob": -1.0564331e-05, "top_logprobs": []}, {"token": " [", "bytes": [32, 91], "logprob": -1.0280384e-06, "top_logprobs": []}, {"token": "out", "bytes": [111, 117, 116], "logprob": -0.00046045915, "top_logprobs": []}, {"token": "door", "bytes": [100, 111, 111, 114], "logprob": -1.7239736e-05, "top_logprobs": []}, {"token": " seating", "bytes": [32, 115, 101, 97, 116, 105, 110, 103], "logprob": -1.3067608e-05, "top_logprobs": []}, {"token": " (", "bytes": [32, 40], "logprob": -2.2007884e-05, "top_logprobs": []}, {"token": "A", "bytes": [65], "logprob": -4.1273333e-06, "top_logprobs": []}, {"token": "men", "bytes": [109, 101, 110], "logprob": 0.0, "top_logprobs": []}, {"token": "ity", "bytes": [105, 116, 121], "logprob": -2.3080716e-05, "top_logprobs": []}, {"token": "),", "bytes": [41, 44], "logprob": -5.2001665e-06, "top_logprobs": []}, {"token": " diverse", "bytes": [32, 100, 105, 118, 101, 114, 115, 101], "logprob": -2.4584822e-06, "top_logprobs": []}, {"token": " menu", "bytes": [32, 109, 101, 110, 117], "logprob": -0.0029024743, "top_logprobs": []}, {"token": " (", "bytes": [32, 40], "logprob": -5.9914648e-05, "top_logprobs": []}, {"token": "A", "bytes": [65], "logprob": -0.060968317, "top_logprobs": []}, {"token": "men", "bytes": [109, 101, 110], "logprob": -1.9361265e-07, "top_logprobs": []}, {"token": "ity", "bytes": [105, 116, 121], "logprob": -5.7961847e-06, "top_logprobs": []}, {"token": ")]", "bytes": [41, 93], "logprob": -0.00021248066, "top_logprobs": []}]