[{"token": "1", "bytes": [49], "logprob": -6.0345924e-06, "top_logprobs": []}, {"token": ".", "bytes": [46], "logprob": -2.3319124e-05, "top_logprobs": []}, {"token": " Text", "bytes": [32, 84, 101, 120, 116], "logprob": -0.05462034, "top_logprobs": []}, {"token": " Span", "bytes": [32, 83, 112, 97, 110], "logprob": -0.003105227, "top_logprobs": []}, {"token": ":", "bytes": [58], "logprob": -7.89631e-07, "top_logprobs": []}, {"token": " \"", "bytes": [32, 34], "logprob": -1.3186812e-05, "top_logprobs": []}, {"token": "exception", "bytes": [101, 120, 99, 101, 112, 116, 105, 111, 110], "logprob": -1.7835755e-05, "top_logprobs": []}, {"token": "al", "bytes": [97, 108], "logprob": -1.3856493e-06, "top_logprobs": []}, {"token": " acting", "bytes": [32, 97, 99, 116, 105, 110, 103], "logprob": -3.2929079e-06, "top_logprobs": []}, {"token": "\"\n", "bytes": [34, 10], "logprob": -0.00043233807, "top_logprobs": []}, {"token": "Label", "bytes": [76, 97, 98, 101, 108], "logprob": -0.33587033, "top_logprobs": []}, {"token": ":", "bytes": [58], "logprob": -7.89631e-07, "top_logprobs": []}, {"token": " (", "bytes": [32, 40], "logprob": -9.603336e-05, "top_logprobs": []}, {"token": "C", "bytes": [67], "logprob": -0.006913218, "top_logprobs": []}, {"token": ").", "bytes": [41, 46], "logprob": -5.9437833e-05, "top_logprobs": []}, {"token": " Wrong", "bytes": [32, 87, 114, 111, 110, 103], "logprob": -0.23523934, "top_logprobs": []}, {"token": " Type", "bytes": [32, 84, 121, 112, 101], "logprob": -0.0010717503, "top_logprobs": []}, {"token": ".", "bytes": [46], "logprob": -5.371606e-05, "top_logprobs": []}, {"token": " The", "bytes": [32, 84, 104, 101], "logprob": -1.7432603e-06, "top_logprobs": []}, {"token": " correct", "bytes": [32, 99, 111, 114, 114, 101, 99, 116], "logprob": -1.9816675e-06, "top_logprobs": []}, {"token": " entity", "bytes": [32, 101, 110, 116, 105, 116, 121], "logprob": -1.831257e-05, "top_logprobs": []}, {"token": " type", "bytes": [32, 116, 121, 112, 101], "logprob": -9.253091e-06, "top_logprobs": []}, {"token": " is", "bytes": [32, 105, 115], "logprob": -8.776276e-06, "top_logprobs": []}, {"token": " other", "bytes": [32, 111, 116, 104, 101, 114], "logprob": -0.2343695, "top_logprobs": []}, {"token": ".\n\n", "bytes": [46, 10, 10], "logprob": -0.0069009056, "top_logprobs": []}, {"token": "2", "bytes": [50], "logprob": -1.1756368e-05, "top_logprobs": []}, {"token": ".", "bytes": [46], "logprob": -1.4617256e-05, "top_logprobs": []}, {"token": " Text", "bytes": [32, 84, 101, 120, 116], "logprob": -0.00017648483, "top_logprobs": []}, {"token": " Span", "bytes": [32, 83, 112, 97, 110], "logprob": -9.968313e-06, "top_logprobs": []}, {"token": ":", "bytes": [58], "logprob": -5.9153886e-06, "top_logprobs": []}, {"token": " \"", "bytes": [32, 34], "logprob": -6.511407e-06, "top_logprobs": []}, {"token": "B", "bytes": [66], "logprob": -2.9994528e-05, "top_logprobs": []}, {"token": "oba", "bytes": [111, 98, 97], "logprob": -2.9352968e-06, "top_logprobs": []}, {"token": " F", "bytes": [32, 70], "logprob": -4.8425554e-06, "top_logprobs": []}, {"token": "ett", "bytes": [101, 116, 116], "logprob": -1.7432603e-06, "top_logprobs": []}, {"token": "\"\n", "bytes": [34, 10], "logprob": -0.00013929696, "top_logprobs": []}, {"token": "Label", "bytes": [76, 97, 98, 101, 108], "logprob": -1.5451682e-05, "top_logprobs": []}, {"token": ":", "bytes": [58], "logprob": -2.8921695e-05, "top_logprobs": []}, {"token": " (", "bytes": [32, 40], "logprob": -8.3874584e-05, "top_logprobs": []}, {"token": "A", "bytes": [65], "logprob": -7.421909e-05, "top_logprobs": []}, {"token": ").", "bytes": [41, 46], "logprob": -4.310693e-05, "top_logprobs": []}, {"token": " The", "bytes": [32, 84, 104, 101], "logprob": -0.009537429, "top_logprobs": []}, {"token": " span", "bytes": [32, 115, 112, 97, 110], "logprob": -2.5345586e-05, "top_logprobs": []}, {"token": " is", "bytes": [32, 105, 115], "logprob": -3.8696395e-05, "top_logprobs": []}, {"token": " a", "bytes": [32, 97], "logprob": -2.3392786e-06, "top_logprobs": []}, {"token": " named", "bytes": [32, 110, 97, 109, 101, 100], "logprob": -2.6968896e-06, "top_logprobs": []}, {"token": " entity", "bytes": [32, 101, 110, 116, 105, 116, 121], "logprob": -3.1782583e-05, "top_logprobs": []}, {"token": " of", "bytes": [32, 111, 102], "logprob": -6.0345924e-06, "top_logprobs": []}, {"token": " type", "bytes": [32, 116, 121, 112, 101], "logprob": -3.0545007e-06, "top_logprobs": []}, {"token": " character", "bytes": [32, 99, 104, 97, 114, 97, 99, 116, 101, 114], "logprob": -0.010889232, "top_logprobs": []}, {"token": "\n\n", "bytes": [10, 10], "logprob": -0.029313581, "top_logprobs": []}, {"token": "3", "bytes": [51], "logprob": -4.723352e-06, "top_logprobs": []}, {"token": ".", "bytes": [46], "logprob": -4.036525e-05, "top_logprobs": []}, {"token": " Text", "bytes": [32, 84, 101, 120, 116], "logprob": -7.529192e-05, "top_logprobs": []}, {"token": " Span", "bytes": [32, 83, 112, 97, 110], "logprob": -7.703444e-06, "top_logprobs": []}, {"token": ":", "bytes": [58], "logprob": -7.226629e-06, "top_logprobs": []}, {"token": " \"", "bytes": [32, 34], "logprob": -9.849109e-06, "top_logprobs": []}, {"token": "Uh", "bytes": [85, 104], "logprob": -1.2113979e-05, "top_logprobs": []}, {"token": "ura", "bytes": [117, 114, 97], "logprob": -1.9027791e-05, "top_logprobs": []}, {"token": "\"\n", "bytes": [34, 10], "logprob": -8.75699e-05, "top_logprobs": []}, {"token": "Label", "bytes": [76, 97, 98, 101, 108], "logprob": -6.9882217e-06, "top_logprobs": []}, {"token": ":", "bytes": [58], "logprob": -3.488188e-05, "top_logprobs": []}, {"token": " (", "bytes": [32, 40], "logprob": -0.000115701965, "top_logprobs": []}, {"token": "A", "bytes": [65], "logprob": -0.0005648266, "top_logprobs": []}, {"token": ").", "bytes": [41, 46], "logprob": -2.9636918e-05, "top_logprobs": []}, {"token": " The", "bytes": [32, 84, 104, 101], "logprob": -5.240482e-05, "top_logprobs": []}, {"token": " span", "bytes": [32, 115, 112, 97, 110], "logprob": -6.1537958e-06, "top_logprobs": []}, {"token": " is", "bytes": [32, 105, 115], "logprob": -7.2907846e-05, "top_logprobs": []}, {"token": " a", "bytes": [32, 97], "logprob": -5.2001665e-06, "top_logprobs": []}, {"token": " named", "bytes": [32, 110, 97, 109, 101, 100], "logprob": -9.0883464e-07, "top_logprobs": []}, {"token": " entity", "bytes": [32, 101, 110, 116, 105, 116, 121], "logprob": -1.0325924e-05, "top_logprobs": []}, {"token": " of", "bytes": [32, 111, 102], "logprob": -2.220075e-06, "top_logprobs": []}, {"token": " type", "bytes": [32, 116, 121, 112, 101], "logprob": -2.3392786e-06, "top_logprobs": []}, {"token": " character", "bytes": [32, 99, 104, 97, 114, 97, 99, 116, 101, 114], "logprob": -0.00127595, "top_logprobs": []}]